{"run_number": "1763071635946981", "step_name": "process_city", "task_id": "2", "attempt_id": 0, "name": "_foreach_stack", "content_type": "gzip+pickle-v4", "type": "metaflow.artifact", "sha": "02b13bc57f2944457fecf45e78b8bafa9b4a5fcc", "ds_type": "local", "location": ":root:/Users/david/Documents/projects/backend/youtube-audio-converter/backend-microservices-converters/demo/metaflow-demo/.metaflow", "flow_id": "CityLatencyFlow", "user_name": "david", "tags": [], "system_tags": ["metaflow_version:2.19.7", "runtime:dev", "user:david", "python_version:3.12.11"], "ts_epoch": 1763071641320}